{"id":14,"category":"Wurzelgemüse","culture":"Karotte","variety":"Gelbe Gochsheimer","rowSpacing":15,"plantingDistance":3,"preGrow":false,"rePot":false,"minGerminationTemp":null,"maxGerminationTemp":null,"quickpotSize":0,"quickpotDuration":0,"seedsPerPot":1,"survivalRate":0.75,"germinationRate":1,"bedDuration":150,"bedKind":"Vlies","harvestRate":1,"harvestUnit":"Stück","numberOfHarvests":1,"harvestInterval":null,"harvestTolerance":80,"comment":"Ganzjahr","description":"","sellingPricePerUnit":0.3}